setup.py
pactors/__init__.py
pactors/core.py
pactors.egg-info/PKG-INFO
pactors.egg-info/SOURCES.txt
pactors.egg-info/dependency_links.txt
pactors.egg-info/top_level.txt