Metadata-Version: 1.0
Name: pactors
Version: 0.0.1
Summary: Python actors library
Home-page: https://github.com/stanislavfeldman/pactors
Author: Stanislav Feldman
Author-email: UNKNOWN
License: UNKNOWN
Keywords: utils actors
Platform: UNKNOWN
Classifier: Development Status :: 3 - Alpha
Classifier: Topic :: Software Development
